pyqcodeeditor/__init__.py
pyqcodeeditor/completers/__init__.py
pyqcodeeditor/completers/QCXXCompleter.py
pyqcodeeditor/completers/QGLSLCompleter.py
pyqcodeeditor/completers/QLuaCompleter.py
pyqcodeeditor/completers/QPythonCompleter.py
pyqcodeeditor/highlighters/__init__.py
pyqcodeeditor/highlighters/QCXXHighlighter.py
pyqcodeeditor/highlighters/QGLSLHighlighter.py
pyqcodeeditor/highlighters/QHighlightBlockRule.py
pyqcodeeditor/highlighters/QHighlightRule.py
pyqcodeeditor/highlighters/QJSONHighlighter.py
pyqcodeeditor/highlighters/QLuaHighlighter.py
pyqcodeeditor/highlighters/QPythonHighlighter.py
pyqcodeeditor/QCodeEditor.py
pyqcodeeditor/QFramedTextAttribute.py
pyqcodeeditor/QLanguage.py
pyqcodeeditor/QLanguageCompleter.py
pyqcodeeditor/QLineNumberArea.py
pyqcodeeditor/QStyleSyntaxHighlighter.py
pyqcodeeditor/QSyntaxStyle.py
pyqcodeeditor/resources/default_style.json
pyqcodeeditor/resources/languages/cxx.json
pyqcodeeditor/resources/languages/glsl.json
pyqcodeeditor/resources/languages/lua.json
pyqcodeeditor/resources/languages/python.json
pyqcodeeditor/utils.py
pyqcodeeditor-0.3.7.dist-info/License
pyqcodeeditor-0.3.7.dist-info/METADATA
pyqcodeeditor-0.3.7.dist-info/WHEEL
pyqcodeeditor-0.3.7.dist-info/RECORD
