Metadata-Version: 2.1
Name: pyqcodeeditor
Version: 0.3.7
Summary: A qtpy implementation of Megaxela’s QCodeEditor (based on C++ Qt).
Author: zimolab
Author-email: zimolab@aliyun.com
Requires-Python: >=3.8,<4.0
Classifier: Programming Language :: Python :: 3
Classifier: Programming Language :: Python :: 3.8
Classifier: Programming Language :: Python :: 3.9
Classifier: Programming Language :: Python :: 3.10
Classifier: Programming Language :: Python :: 3.11
Classifier: Programming Language :: Python :: 3.12
Requires-Dist: qtpy (>=2.4.1,<3.0.0)
